covasant_odata/__init__.py
covasant_odata/clean_filtering_test.py
covasant_odata/cli.py
covasant_odata/connector.py
covasant_odata/count_northwind.py
covasant_odata/main.py
covasant_odata/test_northwind.py
covasant_odata/config/__init__.py
covasant_odata/config/models.py
covasant_odata/config/northwind_config.py
covasant_odata/config/sap_module_mapping.py
covasant_odata/connectors/__init__.py
covasant_odata/connectors/rest_connector.py
covasant_odata/connectors/streaming_connector.py
covasant_odata/error_handling/__init__.py
covasant_odata/error_handling/dead_letter_queue.py
covasant_odata/monitoring/__init__.py
covasant_odata/monitoring/metrics.py
covasant_odata/monitoring/prometheus_config.py
covasant_odata/planning/__init__.py
covasant_odata/planning/graph_builder.py
covasant_odata/planning/plan_generator.py
covasant_odata/planning/record_tracker.py
covasant_odata/services/__init__.py
covasant_odata/services/count.py
covasant_odata/services/metadata.py
covasant_odata/storage/__init__.py
covasant_odata/storage/bigquery_storage.py
covasant_odata/storage/gcs_storage.py
covasant_odata/storage/local_storage.py
covasant_odata/storage/transformer.py
covasant_odata/utils/__init__.py
covasant_odata/utils/log_messages.py
covasant_odata/utils/logging_config.py
covasant_odata/workers/__init__.py
covasant_odata/workers/proxy_pool.py
covasant_odata/workers/resilience.py
covasant_sap_odata_connector-1.0.3.dist-info/licenses/LICENSE
covasant_sap_odata_connector-1.0.3.dist-info/METADATA
covasant_sap_odata_connector-1.0.3.dist-info/WHEEL
covasant_sap_odata_connector-1.0.3.dist-info/top_level.txt
covasant_sap_odata_connector-1.0.3.dist-info/RECORD
