Metadata-Version: 2.4
Name: covasant_sap_odata_connector
Version: 1.0.3
Summary: A powerful Python library for connecting to SAP OData services with OData V2 and V4 support
Author: Covasant Technologies
Author-email: Covasant Technologies <info@covasant.com>
License: MIT
Keywords: sap,odata,connector,api,rest,data,integration,etl
Classifier: Development Status :: 4 - Beta
Classifier: Intended Audience :: Developers
Classifier: Topic :: Software Development :: Libraries :: Python Modules
Classifier: License :: OSI Approved :: MIT License
Classifier: Programming Language :: Python :: 3
Classifier: Programming Language :: Python :: 3.8
Classifier: Programming Language :: Python :: 3.9
Classifier: Programming Language :: Python :: 3.10
Classifier: Programming Language :: Python :: 3.11
Classifier: Programming Language :: Python :: 3.12
Requires-Python: >=3.8
License-File: LICENSE
Requires-Dist: aiohttp>=3.8.0
Requires-Dist: orjson>=3.9.0
Requires-Dist: structlog>=23.1.0
Requires-Dist: pydantic>=2.0.0
Requires-Dist: asyncio>=3.4.3
Requires-Dist: aiolimiter>=1.2.0
Requires-Dist: attrs>=25.0.0
Requires-Dist: coloredlogs>=14.0
Requires-Dist: cryptography>=45.0.0
Requires-Dist: dynaconf>=3.2.0
Requires-Dist: fastapi>=0.116.0
Requires-Dist: google-cloud-bigquery>=3.37.0
Requires-Dist: google-cloud-storage>=3.4.0
Requires-Dist: httpx>=0.28.0
Requires-Dist: lxml>=6.0.0
Requires-Dist: prometheus-client>=0.22.0
Requires-Dist: pybreaker>=1.4.0
Requires-Dist: pyodata>=1.11.0
Requires-Dist: python-dateutil>=2.9.0
Requires-Dist: python-dotenv>=1.1.0
Requires-Dist: PyYAML>=6.0.0
Requires-Dist: requests>=2.32.0
Requires-Dist: SQLAlchemy>=2.0.0
Requires-Dist: tenacity>=9.1.0
Requires-Dist: tqdm>=4.67.0
Requires-Dist: uvicorn>=0.36.0
Requires-Dist: colorama>=0.4.6
Requires-Dist: networkx>=3.0
Provides-Extra: dev
Requires-Dist: pytest>=7.0.0; extra == "dev"
Requires-Dist: pytest-asyncio>=0.21.0; extra == "dev"
Requires-Dist: black>=23.0.0; extra == "dev"
Requires-Dist: flake8>=6.0.0; extra == "dev"
Requires-Dist: mypy>=1.0.0; extra == "dev"
Provides-Extra: bigquery
Requires-Dist: google-cloud-bigquery>=3.0.0; extra == "bigquery"
Dynamic: author
Dynamic: license-file
Dynamic: requires-python
